main.py
module/DES3.py
module/__init__.py
module/utils.py
tdes-0.0.2.dist-info/LICENSE.txt
tdes-0.0.2.dist-info/METADATA
tdes-0.0.2.dist-info/WHEEL
tdes-0.0.2.dist-info/entry_points.txt
tdes-0.0.2.dist-info/top_level.txt
tdes-0.0.2.dist-info/RECORD
