Metadata-Version: 2.1
Name: tdes
Version: 0.0.2
Summary: encrypting and decrypting files tool using triple DES
Home-page: https://github.com/4bd4ll4h/tdes
Author: 4bd4ll4h
Author-email: 4bd4ll4h.m@gmail.com
License: UNKNOWN
Platform: UNKNOWN
Classifier: Topic :: Security :: Cryptography
Classifier: Programming Language :: Python :: 3
Classifier: Programming Language :: Python :: 3.8
Requires-Dist: click
Requires-Dist: pycryptodomex
